mcp_server_sis/__init__.py
mcp_server_sis/__main__.py
mcp_server_sis/sis.py
mcp_server_sis/sis_system.py
mcp_sis-0.1.0.dist-info/licenses/LICENSE
mcp_sis-0.1.0.dist-info/METADATA
mcp_sis-0.1.0.dist-info/WHEEL
mcp_sis-0.1.0.dist-info/entry_points.txt
mcp_sis-0.1.0.dist-info/top_level.txt
mcp_sis-0.1.0.dist-info/RECORD
