Metadata-Version: 2.4
Name: mcp-sis
Version: 0.1.0
Summary: MCP server for CUHKSZ SIS system
Author-email: LKCY23 <lkcydream@gmail.com>
License: MIT
Requires-Python: >=3.9
License-File: LICENSE
Requires-Dist: pytz==2024.2
Requires-Dist: requests==2.30.0
Requires-Dist: urllib3==2.2.3
Requires-Dist: lxml==5.3.0
Requires-Dist: pyOpensSL==24.2.1
Requires-Dist: httpx==0.28.1
Requires-Dist: fastmcp
Requires-Dist: python-dotenv
Dynamic: license-file
